src/aoclib/__init__.py
src/aoclib/lib.py
src/aoclib/load_config.py
python_aoclib-0.2.0.dist-info/LICENSE
python_aoclib-0.2.0.dist-info/WHEEL
python_aoclib-0.2.0.dist-info/METADATA
python_aoclib-0.2.0.dist-info/RECORD
